keboola_api/__init__.py
keboola_api/frontend/index.html
keboola_api/frontend/main.js
keboola_api/frontend/streamlit-component-lib.js
keboola_api/frontend/style.css
keboola_api/frontend/static/icok.png
streamlit_keboola_api-0.2.0.dist-info/LICENSE
streamlit_keboola_api-0.2.0.dist-info/METADATA
streamlit_keboola_api-0.2.0.dist-info/WHEEL
streamlit_keboola_api-0.2.0.dist-info/top_level.txt
streamlit_keboola_api-0.2.0.dist-info/RECORD
