Metadata-Version: 2.1
Name: streamlit-keboola-api
Version: 0.2.0
Summary: Wrapper around Kebolla python client to list tables, buckets and upload files to stage
Author: Anthony Alteirac
Author-email: anthony.alteirac@snowflake.com
Requires-Python: >=3.7
License-File: LICENSE
Requires-Dist: streamlit (>=1.2)
Requires-Dist: jinja2
